mio_client/__init__.py
mio_client/__main__.py
mio_client/cli.py
mio_client/commands/__init__.py
mio_client/commands/gen.py
mio_client/commands/ip.py
mio_client/commands/misc.py
mio_client/commands/sim.py
mio_client/commands/user.py
mio_client/core/__init__.py
mio_client/core/command.py
mio_client/core/configuration.py
mio_client/core/ip.py
mio_client/core/model.py
mio_client/core/phase.py
mio_client/core/root_manager.py
mio_client/core/scheduler.py
mio_client/core/service.py
mio_client/core/user.py
mio_client/core/version.py
mio_client/data/defaults.toml
mio_client/data/doxygen-awesome-darkmode-toggle.js
mio_client/data/doxygen-awesome-sidebar-only-darkmode-toggle.css
mio_client/data/doxygen-awesome-sidebar-only.css
mio_client/data/doxygen-awesome.css
mio_client/data/doxygen.awesome.cfg
mio_client/data/doxygen.private.cfg
mio_client/data/doxygen.public.cfg
mio_client/data/doxygen_footer.html
mio_client/data/doxygen_header.awesome.html
mio_client/data/doxygen_header.html
mio_client/data/doxygen_layout.xml
mio_client/data/doxygen_stylesheet.css
mio_client/data/flist.sv.dsim.j2
mio_client/data/flist.sv.vivado.j2
mio_client/data/flist.vhdl.dsim.j2
mio_client/data/flist.vhdl.vivado.j2
mio_client/data/idv_doxyfilter_sv.pl
mio_client/data/mio_client_user_manual.pdf
mio_client/data/mio_hdl_lic.dsim.sv
mio_client/data/mio_hdl_lic_dpi.dsim.so
mio_client/data/plantuml-1.2024.8.jar
mio_client/data/regression_test_report.html.j2
mio_client/schedulers/__init__.py
mio_client/schedulers/sub_process.py
mio_client/services/__init__.py
mio_client/services/doxygen.py
mio_client/services/fsoc.py
mio_client/services/init.py
mio_client/services/regression.py
mio_client/services/siarx.py
mio_client/services/simulation.py
mooreio_client-2.2.3.dist-info/licenses/LICENSE
tests/__init__.py
tests/conftest.py
tests/test_cli_dox.py
tests/test_cli_init.py
tests/test_cli_ip.py
tests/test_cli_misc.py
tests/test_cli_regr.py
tests/test_cli_sim.py
tests/test_cli_user.py
tests/test_common.py
tests/test_configuration.py
tests/test_core.py
mooreio_client-2.2.3.dist-info/METADATA
mooreio_client-2.2.3.dist-info/WHEEL
mooreio_client-2.2.3.dist-info/entry_points.txt
mooreio_client-2.2.3.dist-info/top_level.txt
mooreio_client-2.2.3.dist-info/RECORD
