Metadata-Version: 2.4
Name: mooreio_client
Version: 2.2.3
Summary: CLI tool to automate EDA tasks for ASICs, FPGAs, and UVM IP.
Home-page: https://github.com/Datum-Technology-Corporation/mooreio_client
Author: Datum Technology Corporation
Author-email: info@datumtc.ca
License: MIT
Project-URL: Web Site, https://www.mooreio.com/
Project-URL: Author, https://www.datumtc.ca/
Project-URL: Documentation, http://mooreio-client.rtfd.io/
Project-URL: Bug Tracker, https://github.com/Datum-Technology-Corporation/mooreio_client/issues
Keywords: SystemVerilog,UVM,DV,verilog,VHDL,hdl,rtl,synthesis,FPGA,simulation,Xilinx,Vivado,Altera,Metrics,DSim
Classifier: Programming Language :: Python :: 3.11
Classifier: License :: OSI Approved :: MIT License
Classifier: Operating System :: OS Independent
Requires-Python: >=3.11
License-File: LICENSE
Requires-Dist: Jinja2>=3.1.6
Requires-Dist: PyYAML>=6.0.3
Requires-Dist: fusesoc>=2.4.5
Requires-Dist: pydantic>=2.12.5
Requires-Dist: requests>=2.32.5
Requires-Dist: rich>=14.2.0
Requires-Dist: semantic_version>=2.10.0
Requires-Dist: toml>=0.10.2
Requires-Dist: tqdm>=4.67.1
Provides-Extra: dev
Requires-Dist: docutils~=0.22.4; extra == "dev"
Requires-Dist: flake8~=7.1.1; extra == "dev"
Requires-Dist: mccabe~=0.7.0; extra == "dev"
Requires-Dist: pycodestyle~=2.12.1; extra == "dev"
Requires-Dist: pyflakes~=3.2.0; extra == "dev"
Requires-Dist: coverage~=7.6.1; extra == "dev"
Requires-Dist: pytest-cov~=5.0.0; extra == "dev"
Requires-Dist: pytest~=8.3.3; extra == "dev"
Requires-Dist: pytest-xdist~=3.6.1; extra == "dev"
Requires-Dist: pytest-metadata~=3.1.1; extra == "dev"
Requires-Dist: flake8-html~=0.4.3; extra == "dev"
Requires-Dist: pygments~=2.18.0; extra == "dev"
Requires-Dist: pytest-html~=4.1.1; extra == "dev"
Requires-Dist: pytest-flake8~=1.3.0; extra == "dev"
Requires-Dist: setuptools~=65.5.0; extra == "dev"
Requires-Dist: fusesoc~=2.4.3; extra == "dev"
Requires-Dist: edalize~=0.6.1; extra == "dev"
Requires-Dist: rich; extra == "dev"
Dynamic: author
Dynamic: author-email
Dynamic: classifier
Dynamic: description
Dynamic: description-content-type
Dynamic: home-page
Dynamic: keywords
Dynamic: license
Dynamic: license-file
Dynamic: project-url
Dynamic: provides-extra
Dynamic: requires-dist
Dynamic: requires-python
Dynamic: summary
